__init__.py
main.py
shipdeo/__init__.py
shipdeo/auth.py
shipdeo/dto.py
shipdeo/shipping.py
python_shipdeo-0.1.0.dist-info/METADATA
python_shipdeo-0.1.0.dist-info/WHEEL
python_shipdeo-0.1.0.dist-info/licenses/LICENSE
python_shipdeo-0.1.0.dist-info/RECORD
