Metadata-Version: 2.1
Name: python-shipdeo
Version: 0.1.0
Summary: A Wrapper Shipdeo Service - 3PL Indonesia Aggregator 
Project-URL: Homepage, https://github.com/xhijack/shipdeo
Project-URL: Bug Tracker, https://github.com/xhijack/shipdeo/issues
Author-email: Ramdani <ramdani@sopwer.net>
License-File: LICENSE
Classifier: License :: OSI Approved :: MIT License
Classifier: Operating System :: OS Independent
Classifier: Programming Language :: Python :: 3
Requires-Python: >=3.7
